openlineage/common/__init__.py
openlineage/common/dataset.py
openlineage/common/models.py
openlineage/common/provider/__init__.py
openlineage/common/provider/bigquery.py
openlineage/common/provider/data-quality-dataset-facet.json
openlineage/common/provider/dbt/__init__.py
openlineage/common/provider/dbt/cloud.py
openlineage/common/provider/dbt/facets.py
openlineage/common/provider/dbt/local.py
openlineage/common/provider/dbt/processor.py
openlineage/common/provider/dbt/structured_logs.py
openlineage/common/provider/dbt/utils.py
openlineage/common/provider/ge-assertions-dataset-facet.json
openlineage/common/provider/great_expectations/__init__.py
openlineage/common/provider/great_expectations/action.py
openlineage/common/provider/great_expectations/facets.py
openlineage/common/provider/great_expectations/results.py
openlineage/common/provider/redshift_data.py
openlineage/common/provider/snowflake.py
openlineage/common/schema/__init__.py
openlineage/common/schema/bq-error-run-facet.json
openlineage/common/schema/bq-statistics-dataset-facet.json
openlineage/common/schema/bq-statistics-run-facet.json
openlineage/common/schema/dbt-node-job-facet.json
openlineage/common/schema/dbt-run-run-facet.json
openlineage/common/schema/dbt-version-run-facet.json
openlineage/common/schema/unknown-source-attribute-run-facet.json
openlineage/common/sql/__init__.py
openlineage/common/test.py
openlineage/common/utils.py
openlineage_integration_common-1.42.1.dist-info/WHEEL
openlineage_integration_common-1.42.1.dist-info/METADATA
openlineage_integration_common-1.42.1.dist-info/RECORD
