Metadata-Version: 2.3
Name: openlineage-integration-common
Version: 1.42.1
Summary: OpenLineage common python library for integrations
Keywords: openlineage
Author: OpenLineage
License: Apache-2.0
Classifier: Development Status :: 5 - Production/Stable
Classifier: Intended Audience :: Developers
Classifier: License :: OSI Approved :: Apache Software License
Classifier: Programming Language :: Python :: 3
Classifier: Programming Language :: Python :: 3.9
Classifier: Programming Language :: Python :: 3.10
Classifier: Programming Language :: Python :: 3.11
Classifier: Programming Language :: Python :: 3.12
Requires-Dist: attrs>=19.3.0
Requires-Dist: openlineage-python
Requires-Dist: openlineage-sql
Requires-Dist: pyyaml>=5.3.1
Requires-Dist: google-api-core>=1.26.3 ; extra == 'bigquery'
Requires-Dist: google-auth>=1.30.0 ; extra == 'bigquery'
Requires-Dist: google-cloud-bigquery>=3,<4.0.0 ; extra == 'bigquery'
Requires-Dist: google-cloud-core>=1.6.0 ; extra == 'bigquery'
Requires-Dist: google-crc32c>=1.1.2 ; extra == 'bigquery'
Requires-Dist: google-api-core>=1.26.3 ; extra == 'dev'
Requires-Dist: google-auth>=1.30.0 ; extra == 'dev'
Requires-Dist: google-cloud-bigquery>=3,<4.0.0 ; extra == 'dev'
Requires-Dist: google-cloud-core>=1.6.0 ; extra == 'dev'
Requires-Dist: google-crc32c>=1.1.2 ; extra == 'dev'
Requires-Dist: great-expectations>=1.0.0 ; extra == 'dev'
Requires-Dist: sqlalchemy>=1.3.24,<2.0.0 ; extra == 'dev'
Requires-Dist: boto3>=1.15.0 ; extra == 'dev'
Requires-Dist: pytest ; extra == 'dev'
Requires-Dist: pytest-cov ; extra == 'dev'
Requires-Dist: pytest-mock ; extra == 'dev'
Requires-Dist: mock ; extra == 'dev'
Requires-Dist: pandas ; extra == 'dev'
Requires-Dist: jinja2 ; extra == 'dev'
Requires-Dist: python-dateutil ; extra == 'dev'
Requires-Dist: mypy>=0.960 ; extra == 'dev'
Requires-Dist: types-python-dateutil ; extra == 'dev'
Requires-Dist: types-pyyaml ; extra == 'dev'
Requires-Dist: ruff ; extra == 'dev'
Requires-Dist: google-api-core>=1.26.3 ; extra == 'dev-no-parser'
Requires-Dist: google-auth>=1.30.0 ; extra == 'dev-no-parser'
Requires-Dist: google-cloud-bigquery>=3,<4.0.0 ; extra == 'dev-no-parser'
Requires-Dist: google-cloud-core>=1.6.0 ; extra == 'dev-no-parser'
Requires-Dist: google-crc32c>=1.1.2 ; extra == 'dev-no-parser'
Requires-Dist: great-expectations>=1.0.0 ; extra == 'dev-no-parser'
Requires-Dist: sqlalchemy>=1.3.24,<2.0.0 ; extra == 'dev-no-parser'
Requires-Dist: boto3>=1.15.0 ; extra == 'dev-no-parser'
Requires-Dist: pytest ; extra == 'dev-no-parser'
Requires-Dist: pytest-cov ; extra == 'dev-no-parser'
Requires-Dist: pytest-mock ; extra == 'dev-no-parser'
Requires-Dist: mock ; extra == 'dev-no-parser'
Requires-Dist: pandas ; extra == 'dev-no-parser'
Requires-Dist: jinja2 ; extra == 'dev-no-parser'
Requires-Dist: python-dateutil ; extra == 'dev-no-parser'
Requires-Dist: mypy>=0.960 ; extra == 'dev-no-parser'
Requires-Dist: types-python-dateutil ; extra == 'dev-no-parser'
Requires-Dist: types-pyyaml ; extra == 'dev-no-parser'
Requires-Dist: great-expectations>=1.0.0 ; extra == 'great-expectations'
Requires-Dist: sqlalchemy>=1.3.24,<2.0.0 ; extra == 'great-expectations'
Requires-Dist: boto3>=1.15.0 ; extra == 'redshift'
Requires-Python: >=3.9
Project-URL: Homepage, https://openlineage.io/
Project-URL: Source, https://github.com/OpenLineage/OpenLineage/tree/main/integration/common
Provides-Extra: bigquery
Provides-Extra: dbt
Provides-Extra: dev
Provides-Extra: dev-no-parser
Provides-Extra: great-expectations
Provides-Extra: redshift
